api_sdk/__init__.py
api_sdk/client.py
api_sdk/exceptions.py
api_sdk/models.py
federated_learning_clinical_safety_sdk-0.1.3.dist-info/METADATA
federated_learning_clinical_safety_sdk-0.1.3.dist-info/WHEEL
federated_learning_clinical_safety_sdk-0.1.3.dist-info/RECORD
